careers/__init__.py
careers/app.py
careers/environment.py
careers/__pycache__/__init__.cpython-39.pyc
careers/game/__init__.py
careers/game/__version__.py
careers/game/actionType.py
careers/game/boardLocation.py
careers/game/borderSquare.py
careers/game/cardDeck.py
careers/game/careersGame.py
careers/game/careersGameEngine.py
careers/game/careersObject.py
careers/game/commandResult.py
careers/game/experienceCard.py
careers/game/experienceCardDeck.py
careers/game/experienceCardType.py
careers/game/gameBoard.py
careers/game/gameEngineCommands.py
careers/game/gameRunner.py
careers/game/gameSquare.py
careers/game/gameState.py
careers/game/gameUtils.py
careers/game/occupation.py
careers/game/occupationSquare.py
careers/game/opportunityCard.py
careers/game/opportunityCardDeck.py
careers/game/opportunityType.py
careers/game/player.py
careers/game/specialProcessing.py
careers/game/successFormula.py
careers/game/__pycache__/__init__.cpython-39.pyc
careers/game/__pycache__/__version__.cpython-39.pyc
careers/server/__init__.py
careers/server/__version__.py
careers/server/app.py
careers/server/gameManager.py
careers-0.0.6.data/data/resources/Amazon_Hi-Tech.json
careers-0.0.6.data/data/resources/Disney_Hi-Tech.json
careers-0.0.6.data/data/resources/ESPN_Hi-Tech.json
careers-0.0.6.data/data/resources/FMC_Hi-Tech.json
careers-0.0.6.data/data/resources/Facebook_Hi-Tech.json
careers-0.0.6.data/data/resources/Google_Hi-Tech.json
careers-0.0.6.data/data/resources/ListerAndBacon_Hi-Tech.json
careers-0.0.6.data/data/resources/Pfizer_Hi-Tech.json
careers-0.0.6.data/data/resources/SpaceX_Hi-Tech.json
careers-0.0.6.data/data/resources/UF_Hi-Tech.json
careers-0.0.6.data/data/resources/collegeDegrees_Hi-Tech.json
careers-0.0.6.data/data/resources/editions.json
careers-0.0.6.data/data/resources/experienceCards_Hi-Tech.json
careers-0.0.6.data/data/resources/gameLayout_Hi-Tech.json
careers-0.0.6.data/data/resources/occupations_Hi-Tech.json
careers-0.0.6.dist-info/LICENSE.txt
careers-0.0.6.dist-info/METADATA
careers-0.0.6.dist-info/WHEEL
careers-0.0.6.dist-info/namespace_packages.txt
careers-0.0.6.dist-info/top_level.txt
careers-0.0.6.dist-info/RECORD
